behavex/.DS_Store
behavex/__init__.py
behavex/__main__.py
behavex/arguments.py
behavex/conf_behavex.cfg
behavex/conf_logging.cfg
behavex/conf_mgr.py
behavex/environment.py
behavex/execution_singleton.py
behavex/global_vars.py
behavex/progress_bar.py
behavex/runner.py
behavex/utils.py
behavex/__pycache__/__init__.cpython-313.pyc
behavex/__pycache__/__init__.cpython-39.pyc
behavex/__pycache__/__main__.cpython-39.pyc
behavex/__pycache__/arguments.cpython-39.pyc
behavex/__pycache__/conf_mgr.cpython-313.pyc
behavex/__pycache__/conf_mgr.cpython-39.pyc
behavex/__pycache__/environment.cpython-313.pyc
behavex/__pycache__/environment.cpython-39.pyc
behavex/__pycache__/execution_singleton.cpython-39.pyc
behavex/__pycache__/global_vars.cpython-313.pyc
behavex/__pycache__/global_vars.cpython-39.pyc
behavex/__pycache__/progress_bar.cpython-39.pyc
behavex/__pycache__/runner.cpython-39.pyc
behavex/__pycache__/utils.cpython-39.pyc
behavex/outputs/__init__.py
behavex/outputs/formatter_manager.py
behavex/outputs/jinja_mgr.py
behavex/outputs/output_strings.py
behavex/outputs/report_html.py
behavex/outputs/report_json.py
behavex/outputs/report_utils.py
behavex/outputs/report_xml.py
behavex/outputs/__pycache__/__init__.cpython-39.pyc
behavex/outputs/__pycache__/formatter_manager.cpython-39.pyc
behavex/outputs/__pycache__/jinja_mgr.cpython-39.pyc
behavex/outputs/__pycache__/output_strings.cpython-39.pyc
behavex/outputs/__pycache__/report_html.cpython-39.pyc
behavex/outputs/__pycache__/report_json.cpython-39.pyc
behavex/outputs/__pycache__/report_utils.cpython-39.pyc
behavex/outputs/__pycache__/report_xml.cpython-39.pyc
behavex/outputs/bootstrap/css/behavex.css
behavex/outputs/bootstrap/css/bootstrap-theme.css
behavex/outputs/bootstrap/css/bootstrap-theme.min.css
behavex/outputs/bootstrap/css/bootstrap-theme.min.css.map
behavex/outputs/bootstrap/css/bootstrap.css
behavex/outputs/bootstrap/css/bootstrap.min.css
behavex/outputs/bootstrap/css/bootstrap.min.css.map
behavex-4.6.0.dist-info/licenses/LICENSE
behavex-4.6.0.dist-info/METADATA
behavex-4.6.0.dist-info/WHEEL
behavex-4.6.0.dist-info/entry_points.txt
behavex-4.6.0.dist-info/top_level.txt
behavex-4.6.0.dist-info/RECORD
