Metadata-Version: 2.4
Name: behavex
Version: 4.6.0
Summary: Agile testing framework on top of Behave (BDD).
Author-email: Hernan Rey <behavex_users@googlegroups.com>
License: The MIT License (MIT)
Project-URL: homepage, https://github.com/hrcorval/behavex
Classifier: Development Status :: 5 - Production/Stable
Classifier: Environment :: Console
Classifier: Intended Audience :: Developers
Classifier: Operating System :: OS Independent
Classifier: Programming Language :: Python
Classifier: Programming Language :: Python :: 3
Classifier: Programming Language :: Python :: 3.5
Classifier: Programming Language :: Python :: 3.6
Classifier: Programming Language :: Python :: 3.7
Classifier: Programming Language :: Python :: 3.8
Classifier: Programming Language :: Python :: 3.9
Classifier: Programming Language :: Python :: 3.10
Classifier: Programming Language :: Python :: 3.11
Classifier: Programming Language :: Python :: 3.12
Classifier: Programming Language :: Python :: 3.13
Classifier: Topic :: Software Development :: Testing
Requires-Python: >=3.5
License-File: LICENSE
Requires-Dist: behave<2.0.0,>=1.2.6
Requires-Dist: behavex-images>=3.3.1
Requires-Dist: allure-python-commons
Requires-Dist: jinja2
Requires-Dist: configobj
Requires-Dist: minify-html
Requires-Dist: csscompressor
Requires-Dist: packaging
Provides-Extra: dev
Requires-Dist: pytest; extra == "dev"
Requires-Dist: pytest-cov; extra == "dev"
Requires-Dist: flake8; extra == "dev"
Requires-Dist: black; extra == "dev"
Dynamic: license-file
